MANIFEST.in
README.rst
setup.py
src/cpinyin/Mandarin.dat
src/cpinyin/__init__.py
src/cpinyin/_cpinyin.pyx
src/cpinyin/tests.py
src/cpinyin.egg-info/PKG-INFO
src/cpinyin.egg-info/SOURCES.txt
src/cpinyin.egg-info/dependency_links.txt
src/cpinyin.egg-info/requires.txt
src/cpinyin.egg-info/top_level.txt