Metadata-Version: 1.1
Name: cpinyin
Version: 0.1.2
Summary: Rewrite lxneng's xpinyin by cython
Home-page: https://github.com/leafcoder/cpinyin
Author: leafcoder
Author-email: leafcoder@gmail.com
License: BSD
Keywords: pinyin xpinyin cpinyin
Platform: UNKNOWN
Classifier: Intended Audience :: Developers
Classifier: License :: OSI Approved :: BSD License
Classifier: Operating System :: OS Independent
Classifier: Programming Language :: Python :: 2
Classifier: Programming Language :: Python :: 2.6
Classifier: Programming Language :: Python :: 2.7
Classifier: Programming Language :: Python :: 3
Classifier: Programming Language :: Python :: 3.3
Classifier: Programming Language :: Python :: 3.4
Classifier: Programming Language :: Python :: 3.5
Classifier: Topic :: Software Development :: Libraries :: Python Modules
